AUTHORS
LICENSE
MANIFEST.in
README.rst
setup.py
django_csv_exports/__init__.py
django_csv_exports/admin.py
django_csv_exports/models.py
django_csv_exports/tests.py
django_csv_exports/views.py
django_django_csv_exports.egg-info/PKG-INFO
django_django_csv_exports.egg-info/SOURCES.txt
django_django_csv_exports.egg-info/dependency_links.txt
django_django_csv_exports.egg-info/not-zip-safe
django_django_csv_exports.egg-info/top_level.txt