Metadata-Version: 1.1
Name: django-django-csv-exports
Version: 1.0.0
Summary: <Include a description of your project>
Home-page: <Include Link to Project>
Author: <Include Your Name Here>
Author-email: <Include Your Email Here>
License: <Include License Name>
Platform: UNKNOWN
Classifier: Topic :: Internet :: WWW/HTTP :: Dynamic Content
Classifier: Intended Audience :: Developers
Classifier: Programming Language :: Python
Classifier: Programming Language :: Python :: 2.6
Classifier: Programming Language :: Python :: 2.7
Classifier: Framework :: Django
Classifier: Development Status :: 4 - Beta
Classifier: Operating System :: OS Independent
